{"song":{"player1":"bf","sectionLengths":[],"player2":"watt","notes":[{"typeOfSection":0,"lengthInSteps":16,"sectionNotes":[],"mustHitSection":false},{"typeOfSection":0,"lengthInSteps":16,"sectionNotes":[],"mustHitSection":true},{"typeOfSection":0,"lengthInSteps":16,"sectionNotes":[],"mustHitSection":false},{"typeOfSection":0,"lengthInSteps":16,"sectionNotes":[],"mustHitSection":true},{"typeOfSection":0,"lengthInSteps":16,"sectionNotes":[],"mustHitSection":false},{"typeOfSection":0,"lengthInSteps":16,"sectionNotes":[[12000,2,0],[12450,3,0],[12900,0,0],[13200,3,0],[13650,1,0],[14100,1,0],[13200,0,0]],"mustHitSection":false},{"typeOfSection":0,"lengthInSteps":16,"sectionNotes":[[14400,3,0],[14850,3,0],[15300,1,0],[15600,3,0],[16050,3,0],[16500,1,0],[14400,1,0],[15600,0,0]],"mustHitSection":false},{"typeOfSection":0,"lengthInSteps":16,"sectionNotes":[[16800,2,0],[18450,1,0],[18900,0,0],[17250,0,0],[17700,3,0],[18000,0,0],[18000,2,0]],"mustHitSection":true},{"typeOfSection":0,"lengthInSteps":16,"sectionNotes":[[19200,3,0],[19650,3,0],[20100,1,0],[20850,3,0],[21300,1,0],[20400,0,0],[19200,0,0],[20400,2,0]],"mustHitSection":true},{"typeOfSection":0,"lengthInSteps":16,"sectionNotes":[[21600,1,0],[22050,2,0],[22500,0,0],[22800,3,0],[23250,1,0],[23700,3,0],[22800,1,0]],"mustHitSection":false},{"typeOfSection":0,"lengthInSteps":16,"sectionNotes":[[24000,0,0],[24450,3,0],[24900,1,0],[25200,0,0],[25650,3,0],[26100,1,0],[24000,2,0],[25200,2,0]],"mustHitSection":false},{"typeOfSection":0,"lengthInSteps":16,"sectionNotes":[[26400,1,0],[26850,2,0],[27600,3,0],[28050,1,0],[28500,3,0],[27300,1,0],[27600,0,0]],"mustHitSection":true},{"typeOfSection":0,"lengthInSteps":16,"sectionNotes":[[28800,3,0],[29250,0,0],[29700,1,0],[30000,2,0],[30450,1,0],[30900,2,0],[28800,1,0],[30000,0,0]],"mustHitSection":true},{"typeOfSection":0,"lengthInSteps":16,"sectionNotes":[[31200,3,300],[31650,1,300],[32100,0,0],[32550,1,300],[31200,0,300],[33000,0,150],[33300,3,150],[33000,2,150],[33300,1,150]],"mustHitSection":false},{"typeOfSection":0,"lengthInSteps":16,"sectionNotes":[[33600,2,300],[34050,1,300],[34950,1,300],[33600,0,300],[34500,3,0],[35400,0,150],[35400,2,150],[35700,1,150],[35700,3,150]],"mustHitSection":false},{"typeOfSection":0,"lengthInSteps":16,"sectionNotes":[[36000,3,300],[36450,1,300],[36900,2,300],[37350,3,300],[36000,0,300],[37800,1,150],[38100,0,150]],"mustHitSection":true},{"typeOfSection":0,"lengthInSteps":16,"sectionNotes":[[38400,2,300],[38850,1,300],[39750,1,300],[38400,0,300],[39300,3,300],[40200,2,150],[40200,0,150],[40500,1,150],[40500,3,150]],"mustHitSection":true},{"typeOfSection":0,"lengthInSteps":16,"sectionNotes":[[40800,1,300],[41250,3,300],[41700,0,450],[42300,2,450],[42900,3,600],[42900,0,600]],"mustHitSection":false},{"typeOfSection":0,"lengthInSteps":16,"sectionNotes":[[44100,3,0],[44250,0,0],[44400,3,450],[45000,1,450],[43800,0,150],[44400,2,450],[45000,0,450]],"mustHitSection":false},{"typeOfSection":0,"lengthInSteps":16,"sectionNotes":[[45600,0,450],[46200,1,450],[46800,2,450],[47400,3,450],[45600,4,450],[46200,5,450],[46800,7,450],[47400,4,450]],"mustHitSection":true},{"typeOfSection":0,"lengthInSteps":16,"sectionNotes":[[48000,1,450],[48600,3,450],[49200,2,450],[49800,0,450],[48600,6,450],[49200,4,450],[49800,6,450],[48000,2,450],[48000,5,450],[48000,4,450],[48600,1,450],[49200,0,450],[48600,5,450],[49200,5,450],[49800,4,450],[49800,3,450]],"mustHitSection":true},{"typeOfSection":0,"lengthInSteps":16,"sectionNotes":[[50400,1,1650]],"mustHitSection":true},{"typeOfSection":0,"lengthInSteps":16,"sectionNotes":[[52800,3,0],[53250,0,0],[53700,2,0],[54000,3,0],[54450,1,0],[54750,0,0],[55050,3,0],[54000,0,0],[55050,1,0]],"mustHitSection":false},{"typeOfSection":0,"lengthInSteps":16,"sectionNotes":[[55350,2,0],[55650,1,0],[56400,3,0],[56700,1,0],[57000,2,0],[55650,2,0],[57000,0,0],[56400,0,0],[56100,1,0]],"mustHitSection":false},{"typeOfSection":0,"lengthInSteps":16,"sectionNotes":[[57600,3,0],[58050,0,0],[58800,3,0],[59250,1,0],[58500,1,0],[59850,2,0],[58800,0,0],[59850,0,0],[59550,3,0]],"mustHitSection":true},{"typeOfSection":0,"lengthInSteps":16,"sectionNotes":[[60150,1,0],[60450,2,0],[60900,1,0],[61200,2,0],[61500,3,0],[61800,2,0],[60450,0,0],[61200,0,0],[61800,1,0]],"mustHitSection":true},{"typeOfSection":0,"lengthInSteps":16,"sectionNotes":[[62400,0,0],[62700,3,0],[62850,1,300],[63300,3,450],[63900,0,300],[62850,0,300],[63300,2,450],[64350,2,150],[64650,3,150]],"mustHitSection":false},{"typeOfSection":0,"lengthInSteps":16,"sectionNotes":[[65850,2,300],[64950,1,150],[65250,0,150],[65550,3,150],[65850,1,300],[66300,0,150],[66600,3,150],[66900,1,150],[66600,0,150],[66900,3,150]],"mustHitSection":false},{"typeOfSection":0,"lengthInSteps":16,"sectionNotes":[[67200,0,0],[67500,3,0],[67650,1,300],[68100,3,0],[68700,1,300],[69150,2,150],[69450,3,150],[69450,0,150],[67650,0,300],[68400,2,150]],"mustHitSection":true},{"typeOfSection":0,"lengthInSteps":16,"sectionNotes":[[69750,1,0],[70050,0,0],[70350,3,0],[70650,2,300],[70650,1,300],[71100,0,150],[71400,1,150],[71400,3,150],[71700,2,150],[71700,0,150]],"mustHitSection":true},{"typeOfSection":0,"lengthInSteps":16,"sectionNotes":[[72000,2,1050],[73200,1,1050]],"mustHitSection":false},{"typeOfSection":0,"lengthInSteps":16,"sectionNotes":[[74400,0,0],[74550,3,0],[74850,0,0],[75150,2,0],[75450,0,0],[75750,3,0],[76050,3,0],[76350,1,300],[74850,1,0],[75150,3,0],[75450,2,0],[75750,1,0],[76050,0,0],[76350,2,300]],"mustHitSection":false},{"lengthInSteps":16,"sectionNotes":[[78000,1,1050],[76800,0,1050]],"typeOfSection":0,"mustHitSection":true,"changeBPM":false,"bpm":100},{"lengthInSteps":16,"sectionNotes":[[79200,0,0],[79350,3,0],[79650,0,0],[80250,0,0],[79200,0,0],[79350,3,0],[79650,0,0],[80250,0,0],[79650,1,0],[80250,2,0],[80850,0,0],[79950,3,0],[80550,3,0],[80850,2,0],[81300,1,0],[81300,3,0]],"typeOfSection":0,"altAnim":false,"mustHitSection":true,"changeBPM":false,"bpm":100},{"sectionNotes":[[81600,4,1050],[82800,7,1050],[82800,2,1050],[81600,1,1050]],"typeOfSection":0,"lengthInSteps":16,"altAnim":false,"mustHitSection":false,"changeBPM":false,"bpm":100},{"sectionNotes":[[84000,0,0],[84450,3,0],[84600,1,300],[85050,3,0],[85350,1,0],[85650,3,0],[85200,7,1050],[85950,0,300],[84000,3,0],[84450,2,0],[85050,0,0],[85650,1,0],[85950,2,300],[84150,1,150],[84000,5,1050]],"typeOfSection":0,"lengthInSteps":16,"altAnim":false,"mustHitSection":false,"changeBPM":false,"bpm":90},{"sectionNotes":[[86400,1,1050],[87600,2,1050],[86400,4,1050],[87600,7,1050]],"typeOfSection":0,"lengthInSteps":16,"altAnim":false,"mustHitSection":true,"changeBPM":false,"bpm":90},{"sectionNotes":[[88800,6,1050],[90000,5,1050],[88800,3,150],[89550,3,0],[89100,1,0],[89250,0,0],[88800,0,150],[89550,1,0],[89850,0,600],[89250,2,0],[89850,3,600]],"typeOfSection":0,"lengthInSteps":16,"altAnim":false,"mustHitSection":true,"changeBPM":false,"bpm":100},{"sectionNotes":[[92400,0,1050],[92400,4,1050],[91200,5,1050],[91200,3,1050]],"typeOfSection":0,"lengthInSteps":16,"altAnim":false,"mustHitSection":false,"changeBPM":false,"bpm":100},{"sectionNotes":[[93600,5,1050],[94800,7,450],[95400,6,450],[93600,0,0],[93900,1,0],[94200,3,0],[94500,1,0],[94800,2,0],[95400,1,0],[95700,3,0],[93600,2,0],[94200,0,0],[94800,0,0],[95100,3,0],[95400,2,0]],"typeOfSection":0,"lengthInSteps":16,"altAnim":false,"mustHitSection":false,"changeBPM":false,"bpm":100},{"sectionNotes":[[96000,6,0],[96300,4,0],[96600,5,0],[97200,2,0],[97500,0,0],[97800,1,0],[96000,4,0],[96600,7,0],[96900,6,0],[97200,0,0],[97800,3,0],[98100,2,0]],"typeOfSection":0,"lengthInSteps":16,"altAnim":false,"mustHitSection":true,"changeBPM":false,"bpm":100},{"sectionNotes":[[98400,6,150],[98700,4,150],[99000,5,150],[99600,6,150],[99900,4,150],[100200,5,150],[98700,1,150],[98400,3,150],[99000,0,150],[99600,3,150],[99900,1,150],[100200,0,150],[100500,2,150],[98400,0,150],[99000,2,150],[99300,1,150],[100200,2,150],[98400,4,150],[99000,7,150],[99300,6,150],[99600,4,150],[99600,0,150],[100200,7,150],[100500,6,150]],"typeOfSection":0,"lengthInSteps":16,"altAnim":false,"mustHitSection":true,"changeBPM":false,"bpm":100},{"sectionNotes":[[100800,5,600],[100800,1,750]],"typeOfSection":0,"lengthInSteps":16,"altAnim":false,"mustHitSection":true,"changeBPM":false,"bpm":100},{"lengthInSteps":16,"typeOfSection":0,"sectionNotes":[],"altAnim":false,"bpm":100,"changeBPM":false,"mustHitSection":true},{"sectionNotes":[],"typeOfSection":0,"lengthInSteps":16,"altAnim":false,"mustHitSection":true,"changeBPM":false,"bpm":100},{"lengthInSteps":16,"typeOfSection":0,"sectionNotes":[],"altAnim":false,"bpm":100,"changeBPM":false,"mustHitSection":true},{"lengthInSteps":16,"typeOfSection":0,"sectionNotes":[],"altAnim":false,"bpm":100,"changeBPM":false,"mustHitSection":true},{"lengthInSteps":16,"typeOfSection":0,"sectionNotes":[],"altAnim":false,"bpm":100,"changeBPM":false,"mustHitSection":true},{"sectionNotes":[],"typeOfSection":0,"lengthInSteps":16,"altAnim":false,"mustHitSection":true,"changeBPM":false,"bpm":100},{"lengthInSteps":16,"altAnim":false,"typeOfSection":0,"sectionNotes":[],"bpm":100,"changeBPM":false,"mustHitSection":true}],"song":"Spark","validScore":true,"sections":0,"needsVoices":true,"bpm":100,"speed":1.8}}